MANIFEST.in
README.md
package.json
setup.py
./setup.py
./images/__init__.py
./lib/jasmine-core/__init__.py
./lib/jasmine-core/core.py
./node_modules/walkdir/test/comparison/find.py
images/__init__.py
images/jasmine-horizontal.png
images/jasmine_favicon.png
jasmine_core.egg-info/PKG-INFO
jasmine_core.egg-info/SOURCES.txt
jasmine_core.egg-info/dependency_links.txt
jasmine_core.egg-info/requires.txt
jasmine_core.egg-info/top_level.txt
lib/jasmine-core/__init__.py
lib/jasmine-core/boot.js
lib/jasmine-core/boot0.js
lib/jasmine-core/boot1.js
lib/jasmine-core/core.py
lib/jasmine-core/jasmine-html.js
lib/jasmine-core/jasmine.css
lib/jasmine-core/jasmine.js
lib/jasmine-core/json2.js
lib/jasmine-core/node_boot.js